reactionmenu/__init__.py
reactionmenu/abc.py
reactionmenu/buttons.py
reactionmenu/core.py
reactionmenu/decorators.py
reactionmenu/errors.py
reactionmenu/views_menu.py
reactionmenu-3.1.7.dist-info/LICENSE
reactionmenu-3.1.7.dist-info/METADATA
reactionmenu-3.1.7.dist-info/WHEEL
reactionmenu-3.1.7.dist-info/top_level.txt
reactionmenu-3.1.7.dist-info/RECORD
