Metadata-Version: 2.1
Name: reactionmenu
Version: 3.1.7
Summary: A library to create a discord.py 2.0+ paginator. Supports pagination with buttons, reactions, and category selection using selects.
Author: Defxult
License: MIT
Project-URL: Homepage, https://github.com/Defxult/reactionmenu
Project-URL: Changelog, https://github.com/Defxult/reactionmenu/blob/main/CHANGELOG.md
Keywords: buttons,buttons paginator,buttons menu,discord,discord.py,discord.py 2.0,d.py,components,components paginator,components menu,discord components,discord components menu,discord buttons,discord buttons paginator,discord buttons menu,discord paginator,discord pagination,discord reaction menu,discord reactions,discord embed,discord menu,discord interactions,embed menu,embed reaction menu,embed paginator,interactions,interactions menu,interactions paginator,menus,paginator,pagination,pagin
Classifier: Development Status :: 5 - Production/Stable
Classifier: Programming Language :: Python :: 3
Classifier: Programming Language :: Python :: 3.8
Classifier: Programming Language :: Python :: 3.9
Classifier: Programming Language :: Python :: 3.10
Classifier: Programming Language :: Python :: 3.11
Classifier: Programming Language :: Python :: 3.12
Classifier: Topic :: Software Development :: Libraries
Classifier: Topic :: Software Development :: Libraries :: Python Modules
Requires-Python: >=3.8
License-File: LICENSE
Requires-Dist: discord.py>=2.0.0
